{
  "schemaVersion": 1,
  "userId": "21y337tnjcnnjntvxssctfnda",
  "cacheKey": "track_11FoY6Yj3iknqKuky8yv46_artists",
  "fetchedAt": "2026-03-03T22:20:21.211Z",
  "lastRefreshedAt": "2026-03-03T22:20:21.211Z",
  "data": {
    "artists": [
      {
        "id": "3lmszXxkp47K9kDCRRPU8p",
        "name": "Laddi Chahal"
      },
      {
        "id": "55kkrbuMkdzPGD7YGA6xrJ",
        "name": "Gurlez Akhtar"
      },
      {
        "id": "3OQRPFFS3OsltFjFAXu1kE",
        "name": "Parmish Verma"
      }
    ]
  }
}