{
  "schemaVersion": 1,
  "userId": "mock_demo",
  "cacheKey": "artist_0gadJ2b9A4SKsB1RFkBb66_profile",
  "fetchedAt": "2026-03-20T00:34:25.480Z",
  "lastRefreshedAt": "2026-03-20T00:34:25.480Z",
  "data": {
    "id": "0gadJ2b9A4SKsB1RFkBb66",
    "name": "Passenger",
    "imageUrl": "https://i.scdn.co/image/ab6761610000e5eba340be7e0bd2c71a3f2ca9ce",
    "images": [
      {
        "url": "https://i.scdn.co/image/ab6761610000e5eba340be7e0bd2c71a3f2ca9ce",
        "height": 640,
        "width": 640
      },
      {
        "url": "https://i.scdn.co/image/ab67616100005174a340be7e0bd2c71a3f2ca9ce",
        "height": 320,
        "width": 320
      },
      {
        "url": "https://i.scdn.co/image/ab6761610000f178a340be7e0bd2c71a3f2ca9ce",
        "height": 160,
        "width": 160
      }
    ],
    "externalUrl": "https://open.spotify.com/artist/0gadJ2b9A4SKsB1RFkBb66",
    "genres": [],
    "popularity": null,
    "followersTotal": null
  }
}